polyline/__init__.py
polyline/polyline.py
polyline-2.0.1.dist-info/LICENSE
polyline-2.0.1.dist-info/METADATA
polyline-2.0.1.dist-info/WHEEL
polyline-2.0.1.dist-info/top_level.txt
polyline-2.0.1.dist-info/RECORD
