Metadata-Version: 2.1
Name: polyline
Version: 2.0.1
Summary: A Python implementation of Google's Encoded Polyline Algorithm Format.
Author: Frederick Jansen, Bruno M. Custódio
License: Copyright (c) 2023 Frederick Jansen
Project-URL: homepage, https://github.com/frederickjansen/polyline
Project-URL: repository, https://github.com/frederickjansen/polyline
Requires-Python: >=3.7
License-File: LICENSE
Provides-Extra: dev
Requires-Dist: pytest~=7.0; extra == "dev"
Requires-Dist: pytest-cov~=4.0; extra == "dev"
Requires-Dist: pylint~=2.15.10; extra == "dev"
Requires-Dist: sphinx~=4.2.0; extra == "dev"
Requires-Dist: sphinx-rtd-theme~=1.0.0; extra == "dev"
Requires-Dist: toml~=0.10.2; extra == "dev"
Provides-Extra: publish
Requires-Dist: build~=0.8; extra == "publish"
Requires-Dist: twine~=4.0; extra == "publish"
